dpx2ffv1/__init__.py
dpx2ffv1/__main__.py
dpx2ffv1/dpx2ffv1.py
dpx2ffv1/encode.py
dpx2ffv1/fileutils.py
dpx2ffv1/test.py
dpx2ffv1-0.1.0.dist-info/LICENSE-WTFPL
dpx2ffv1-0.1.0.dist-info/METADATA
dpx2ffv1-0.1.0.dist-info/WHEEL
dpx2ffv1-0.1.0.dist-info/entry_points.txt
dpx2ffv1-0.1.0.dist-info/top_level.txt
dpx2ffv1-0.1.0.dist-info/RECORD
